json2onnx/__init__.py
json2onnx/__main__.py
json2onnx/json2onnx.py
json2onnx-2.0.3.dist-info/LICENSE
json2onnx-2.0.3.dist-info/METADATA
json2onnx-2.0.3.dist-info/WHEEL
json2onnx-2.0.3.dist-info/entry_points.txt
json2onnx-2.0.3.dist-info/top_level.txt
json2onnx-2.0.3.dist-info/RECORD
