Metadata-Version: 2.1
Name: json2onnx
Version: 2.0.3
Summary: Converts a JSON file to an ONNX file.
Home-page: https://github.com/PINTO0309/json2onnx
Author: Katsuya Hyodo
Author-email: rmsdh122@yahoo.co.jp
License: MIT License
Platform: linux
Platform: unix
Requires-Python: >=3.6
License-File: LICENSE
